azure_shell-0.2.5.dist-info/DESCRIPTION.rst
azure_shell-0.2.5.dist-info/METADATA
azure_shell-0.2.5.dist-info/RECORD
azure_shell-0.2.5.dist-info/WHEEL
azure_shell-0.2.5.dist-info/entry_points.txt
azure_shell-0.2.5.dist-info/metadata.json
azure_shell-0.2.5.dist-info/top_level.txt
azureshell/__init__.py
azureshell/azureshell.conf
azureshell/azureshell.py
azureshell/cache.py
azureshell/compat.py
azureshell/completer.py
azureshell/config.py
azureshell/index.py
azureshell/index_generator.py
azureshell/lexer.py
azureshell/logger.py
azureshell/utils.py
