Metadata-Version: 2.0
Name: azure-shell
Version: 0.2.5
Summary: An interactive Azure CLI 2.0 command line interface
Home-page: https://github.com/yokawasa/azure-shell
Author: Yoichi Kawasaki
Author-email: yoichi.kawasaki@outlook.com
License: Apache License 2.0
Download-URL: https://pypi.python.org/pypi/azure-shell
Keywords: azure azure-shell,shell,azure-cli
Platform: any
Classifier: Environment :: Console
Classifier: Intended Audience :: Developers
Classifier: Intended Audience :: System Administrators
Classifier: Natural Language :: English
Classifier: License :: OSI Approved :: Apache Software License
Classifier: Programming Language :: Python
Classifier: Programming Language :: Python :: 2.7
Classifier: Programming Language :: Python :: 3
Classifier: Programming Language :: Python :: 3.3
Classifier: Programming Language :: Python :: 3.4
Classifier: Programming Language :: Python :: 3.5
Classifier: Programming Language :: Python :: 3.6
Requires-Dist: Pygments (>=2.1.3,<3.0.0)
Requires-Dist: configparser (>=3.5.0)
Requires-Dist: prompt-toolkit (<1.1.0,>=1.0.0)
Requires-Dist: pyyaml
